cobsurv/__init__.py
cobsurv/utils.py
cobsurv/models/__init__.py
cobsurv/models/cobrasurvival.py
cobsurv/models/distance_functions.py
cobsurv/models/indexcalculator.py
cobsurv/models/npsurvival_models.py
cobsurv-0.0.1.dist-info/LICENSE
cobsurv-0.0.1.dist-info/METADATA
cobsurv-0.0.1.dist-info/WHEEL
cobsurv-0.0.1.dist-info/top_level.txt
cobsurv-0.0.1.dist-info/RECORD
